do_pod_dns_controller/__init__.py
do_pod_dns_controller/controller.py
do_pod_dns_controller-0.1.2.dist-info/LICENSE
do_pod_dns_controller-0.1.2.dist-info/METADATA
do_pod_dns_controller-0.1.2.dist-info/WHEEL
do_pod_dns_controller-0.1.2.dist-info/entry_points.txt
do_pod_dns_controller-0.1.2.dist-info/top_level.txt
do_pod_dns_controller-0.1.2.dist-info/RECORD
