Metadata-Version: 2.1
Name: do-pod-dns-controller
Version: 0.1.2
Summary: Controller for exposing pod nodeIPs via DNS on DigitalOcean.
Home-page: https://github.com/seanlynch/do-pod-dns-controller
Author: Sean Lynch
Author-email: seanl@literati.org
License: UNKNOWN
Platform: UNKNOWN
Classifier: Programming Language :: Python :: 3
Classifier: License :: OSI Approved :: Apache Software License
Classifier: Operating System :: OS Independent
Requires-Python: >=3.8
Requires-Dist: python-digitalocean
Requires-Dist: kubernetes
